i3a/__init__.py
i3a/cycle_focus.py
i3a/master_stack.py
i3a/move_to_empty.py
i3a/resize_compass.py
i3a/scale_cycle.py
i3a/swallow.py
i3a/swap.py
i3a/trail.py
i3a-2.4.0.dist-info/METADATA
i3a-2.4.0.dist-info/WHEEL
i3a-2.4.0.dist-info/entry_points.txt
i3a-2.4.0.dist-info/licenses/LICENSE
i3a-2.4.0.dist-info/RECORD
