Metadata-Version: 2.4
Name: i3a
Version: 2.4.0
Summary: Automatic manager for i3 tiling
Author-email: Michal Goral <dev@goral.net.pl>
License-Expression: GPL-3.0-or-later
License-File: LICENSE
Classifier: Development Status :: 5 - Production/Stable
Classifier: Environment :: Console
Classifier: Intended Audience :: End Users/Desktop
Classifier: License :: OSI Approved :: GNU General Public License v3 or later (GPLv3+)
Classifier: Natural Language :: English
Classifier: Operating System :: POSIX
Classifier: Programming Language :: Python :: 3 :: Only
Classifier: Topic :: Utilities
Requires-Python: >=3.11
Requires-Dist: i3ipc==2.2.1
